README.md
setup.cfg
setup.py
yandex/__init__.py
yandex/client.py
yandex/errors.py
yandex/requester.py
yandex_api.egg-info/PKG-INFO
yandex_api.egg-info/SOURCES.txt
yandex_api.egg-info/dependency_links.txt
yandex_api.egg-info/requires.txt
yandex_api.egg-info/top_level.txt